mepsy/__init__.py
mepsy/_version.py
mepsy/env.py
mepsy/spark.py
mepsy-0.0.7.dist-info/METADATA
mepsy-0.0.7.dist-info/WHEEL
mepsy-0.0.7.dist-info/RECORD
